avtdl.py
avtdl/__init__.py
avtdl/_version.py
avtdl/avtdl.py
avtdl/core/__init__.py
avtdl/core/actions.py
avtdl/core/actors.py
avtdl/core/cache.py
avtdl/core/chain.py
avtdl/core/config.py
avtdl/core/cookies.py
avtdl/core/db.py
avtdl/core/formatters.py
avtdl/core/info.py
avtdl/core/interfaces.py
avtdl/core/loggers.py
avtdl/core/monitors.py
avtdl/core/plugins.py
avtdl/core/request.py
avtdl/core/runtime.py
avtdl/core/state.py
avtdl/core/utils.py
avtdl/core/webui.py
avtdl/core/yaml.py
avtdl/plugins/__init__.py
avtdl/plugins/discord/__init__.py
avtdl/plugins/discord/webhook.py
avtdl/plugins/execute/__init__.py
avtdl/plugins/execute/run_command.py
avtdl/plugins/fc2/__init__.py
avtdl/plugins/fc2/fc2.py
avtdl/plugins/file/__init__.py
avtdl/plugins/file/download.py
avtdl/plugins/file/text_file.py
avtdl/plugins/filters/__init__.py
avtdl/plugins/filters/filters.py
avtdl/plugins/filters/format.py
avtdl/plugins/iwara/__init__.py
avtdl/plugins/iwara/iwara.py
avtdl/plugins/nitter/__init__.py
avtdl/plugins/nitter/nitter.py
avtdl/plugins/rplay/__init__.py
avtdl/plugins/rplay/rplay.py
avtdl/plugins/rss/__init__.py
avtdl/plugins/rss/generic_rss.py
avtdl/plugins/twitcast/__init__.py
avtdl/plugins/twitcast/twitcast_monitor.py
avtdl/plugins/twitch/__init__.py
avtdl/plugins/twitch/twitch.py
avtdl/plugins/twitter/__init__.py
avtdl/plugins/twitter/endpoints.py
avtdl/plugins/twitter/extractors.py
avtdl/plugins/twitter/filters.py
avtdl/plugins/twitter/spaces.py
avtdl/plugins/twitter/twitter.py
avtdl/plugins/url/__init__.py
avtdl/plugins/url/url.py
avtdl/plugins/utils/__init__.py
avtdl/plugins/utils/utils.py
avtdl/plugins/view/__init__.py
avtdl/plugins/view/view.py
avtdl/plugins/withny/__init__.py
avtdl/plugins/withny/extractors.py
avtdl/plugins/withny/withny.py
avtdl/plugins/withny/withny_live.py
avtdl/plugins/xmpp/__init__.py
avtdl/plugins/xmpp/msg2jbr_aioxmpp.py
avtdl/plugins/xmpp/msg2jbr_slixmpp.py
avtdl/plugins/xmpp/send_jabber.py
avtdl/plugins/youtube/__init__.py
avtdl-2.10.1.dist-info/LICENSE
avtdl-2.10.1.dist-info/METADATA
avtdl-2.10.1.dist-info/WHEEL
avtdl-2.10.1.dist-info/entry_points.txt
avtdl-2.10.1.dist-info/top_level.txt
avtdl-2.10.1.dist-info/RECORD
