Metadata-Version: 2.2
Name: avtdl
Version: 2.10.1
Summary: Monitoring and automation tool for Youtube and other streaming platforms
Author: 15532th
Project-URL: Homepage, https://github.com/15532th/avtdl
Project-URL: Documentation, https://github.com/15532th/avtdl
Project-URL: Repository, https://github.com/15532th/avtdl.git
Project-URL: Issues, https://github.com/15532th/avtdl/issues
Classifier: Environment :: Console
Classifier: License :: OSI Approved :: MIT License
Requires-Python: >=3.9
License-File: LICENSE
Requires-Dist: pydantic>=2.7.0
Requires-Dist: aiohttp<3.10,>=3.9; sys_platform == "win32"
Requires-Dist: aiohttp>=3.9; sys_platform != "win32"
Requires-Dist: curl_cffi
Requires-Dist: multidict
Requires-Dist: feedparser
Requires-Dist: python-dateutil
Requires-Dist: slixmpp==1.8.6
Requires-Dist: lxml
Requires-Dist: ruamel.yaml>=0.15
Requires-Dist: Markdown
Requires-Dist: jsonpath-python==1.0.6
